xenopict/__init__.py
xenopict/_cm_def.py
xenopict/_static_version.py
xenopict/_version.py
xenopict/alignment.py
xenopict/colormap.py
xenopict/drawer.py
xenopict/magic.py
xenopict/monkey.py
xenopict/plotdot.py
xenopict/svg.py
xenopict/declarative/__init__.py
xenopict/declarative/types.py
xenopict/tests/__init__.py
xenopict/tests/test_align.py
xenopict/tests/test_declarative.py
xenopict/tests/test_patcher.py
xenopict/tests/test_xenopict.py
xenopict-0.3.dist-info/METADATA
xenopict-0.3.dist-info/WHEEL
xenopict-0.3.dist-info/licenses/LICENSE
xenopict-0.3.dist-info/RECORD
